SportsCardTool/__init__.py
SportsCardTool/_version.py
SportsCardTool/bref_tool.py
SportsCardTool/ebay_tool.py
SportsCardTool/scraping_tool.py
SportsCardTool/searching_tool.py
SportsCardTool/statcast_tool.py
SportsCardTool/util.py
SportsCardTool/data/bref_data.json
SportsCardTool/tests/test_all.py
SportsCardTool-0.2.4.dist-info/LICENSE
SportsCardTool-0.2.4.dist-info/METADATA
SportsCardTool-0.2.4.dist-info/WHEEL
SportsCardTool-0.2.4.dist-info/top_level.txt
SportsCardTool-0.2.4.dist-info/RECORD
